LICENSE
README.md
setup.py
weather_data_retriever/__init__.py
weather_data_retriever/pipelines.py
weather_data_retriever/utils.py
weather_data_retriever.egg-info/PKG-INFO
weather_data_retriever.egg-info/SOURCES.txt
weather_data_retriever.egg-info/dependency_links.txt
weather_data_retriever.egg-info/requires.txt
weather_data_retriever.egg-info/top_level.txt