Metadata-Version: 2.1
Name: weather-data-retriever
Version: 0.2.2
Summary: Weather data retriever
Home-page: https://github.com/stavrostheocharis/weather_data_retriever.git
Author: Stavros Theocharis
Author-email: stavrostheocharis@yahoo.gr
License: MIT License
Keywords: weather data,historical data,meteo data,nasa data
Classifier: Development Status :: 4 - Beta
Classifier: Intended Audience :: Developers
Classifier: Topic :: Software Development :: Build Tools
Classifier: License :: OSI Approved :: MIT License
Classifier: Programming Language :: Python :: 3.8
Classifier: Programming Language :: Python :: 3.9
Classifier: Programming Language :: Python :: 3.10
Classifier: Programming Language :: Python :: 3.11
License-File: LICENSE
Requires-Dist: pandas
Requires-Dist: geopy
Requires-Dist: requests
